yaqd_gdrive/VERSION
yaqd_gdrive/__init__.py
yaqd_gdrive/__version__.py
yaqd_gdrive/_gdrive.py
yaqd_gdrive/gdrive.avpr
yaqd_gdrive/gdrive.toml
yaqd_gdrive-2021.10.0.dist-info/entry_points.txt
yaqd_gdrive-2021.10.0.dist-info/LICENSE
yaqd_gdrive-2021.10.0.dist-info/WHEEL
yaqd_gdrive-2021.10.0.dist-info/METADATA
yaqd_gdrive-2021.10.0.dist-info/RECORD
