Metadata-Version: 2.1
Name: yaqd-gdrive
Version: 2021.10.0
Summary: Daemon interface for writing files to Google Drive
Home-page: https://yaq.fyi
Author: yaq developers
Author-email: git@ksunden.space
Requires-Python: >=3.7
Classifier: Development Status :: 2 - Pre-Alpha
Classifier: Intended Audience :: Science/Research
Classifier: License :: OSI Approved :: GNU Lesser General Public License v3 (LGPLv3)
Classifier: Natural Language :: English
Classifier: Programming Language :: Python :: 3
Classifier: Programming Language :: Python :: 3.7
Classifier: Programming Language :: Python :: 3.8
Classifier: Topic :: Scientific/Engineering
Requires-Dist: yaqd-core>=2020.06.3
Requires-Dist: aiohttp
Requires-Dist: black ; extra == "dev"
Requires-Dist: pre-commit ; extra == "dev"
Project-URL: Issues, https://gitlab.com/yaq/yaqd-gdrive/issues
Project-URL: Source, https://gitlab.com/yaq/yaqd-gdrive
Provides-Extra: dev
